LICENSE
losuapi/__init__.py
losuapi/AsyncOsuApi.py
losuapi/BaseOsuApi.py
losuapi/OsuApi.py
losuapi/types/__init__.py
losuapi/types/Beatmap.py
losuapi/types/Beatmapset.py
losuapi/types/Covers.py
losuapi/types/DifficultyAttributes.py
losuapi/types/Enums.py
losuapi/types/Event.py
losuapi/types/Extras.py
losuapi/types/KudosuHistory.py
losuapi/types/Rankings.py
losuapi/types/Score.py
losuapi/types/User.py
losuapi/types/UserExtras.py
losuapi/types/UserStatistics.py
losuapi/utility.py
losuapi-0.2.2.dist-info/LICENSE
losuapi-0.2.2.dist-info/METADATA
losuapi-0.2.2.dist-info/WHEEL
losuapi-0.2.2.dist-info/RECORD
