Metadata-Version: 2.1
Name: losuapi
Version: 0.2.2
Summary: Python wrapper for the Osu apiV2
Home-page: https://github.com/LiskIsBest/Losuapi
License: MIT
Keywords: python,osu,api,wrapper
Author: Darien Moore
Author-email: LiskIsBest@gmail.com
Requires-Python: >=3.10,<4.0
Classifier: License :: OSI Approved :: MIT License
Classifier: Programming Language :: Python :: 3
Classifier: Programming Language :: Python :: 3.10
Classifier: Programming Language :: Python :: 3.11
Requires-Dist: anyio (==3.6.2)
Requires-Dist: certifi (==2022.12.7)
Requires-Dist: h11 (==0.14.0)
Requires-Dist: httpcore (==0.16.3)
Requires-Dist: httpx (==0.23.3)
Requires-Dist: idna (==3.4)
Requires-Dist: pydantic (==1.10.4)
Requires-Dist: rfc3986 (==1.5.0)
Requires-Dist: sniffio (==1.3.0)
Requires-Dist: typing-extensions (==4.4.0)
Project-URL: Repository, https://github.com/LiskIsBest/Losuapi/tree/v0.2.2
